configify
configify.py
setup.py
Configify.egg-info/PKG-INFO
Configify.egg-info/SOURCES.txt
Configify.egg-info/dependency_links.txt
Configify.egg-info/requires.txt
Configify.egg-info/top_level.txt