Metadata-Version: 1.0
Name: Configify
Version: 0.0.3
Summary: Templated output, from templated context parameters
Home-page: https://github.com/RickyCook/configify
Author: Ricky Cook
Author-email: mail@thatpanda.com
License: UNKNOWN
Platform: UNKNOWN
